{
  "title": "⚠️ TRANSLATION NEEDED ⚠️",
  "separator": "⚠️ TRANSLATION NEEDED ⚠️",
  "mainDebuggerSystemDiagnostics": "⚠️ TRANSLATION NEEDED ⚠️",
  "consoleTranslationsCheck": "⚠️ TRANSLATION NEEDED ⚠️",
  "exportMissingKeys": "⚠️ TRANSLATION NEEDED ⚠️",
  "replaceHardcodedConsole": "⚠️ TRANSLATION NEEDED ⚠️",
  "consoleKeyChecker": "⚠️ TRANSLATION NEEDED ⚠️",
  "debugLogs": "⚠️ TRANSLATION NEEDED ⚠️",
  "backToMainMenu": "⚠️ TRANSLATION NEEDED ⚠️",
  "selectOption": "⚠️ TRANSLATION NEEDED ⚠️",
  "runningDebugTool": "⚠️ TRANSLATION NEEDED ⚠️",
  "debugToolNotFound": "⚠️ TRANSLATION NEEDED ⚠️",
  "recentDebugLogs": "⚠️ TRANSLATION NEEDED ⚠️",
  "noDebugLogsFound": "⚠️ TRANSLATION NEEDED ⚠️",
  "debugLogsDirectoryNotFound": "⚠️ TRANSLATION NEEDED ⚠️",
  "selectLogPrompt": "⚠️ TRANSLATION NEEDED ⚠️",
  "invalidChoiceSelectRange": "⚠️ TRANSLATION NEEDED ⚠️",
  "contentOf": "⚠️ TRANSLATION NEEDED ⚠️",
  "pressEnterToContinue": "⚠️ TRANSLATION NEEDED ⚠️"
}